quay_client/__init__.py
quay_client-7.dist-info/DESCRIPTION.rst
quay_client-7.dist-info/METADATA
quay_client-7.dist-info/RECORD
quay_client-7.dist-info/WHEEL
quay_client-7.dist-info/metadata.json
quay_client-7.dist-info/top_level.txt
