Metadata-Version: 2.0
Name: quay-client
Version: 7
Summary: Provide a client for quay.io
Home-page: https://github.com/tinyclues/quay_client
Author: Damien Goldenberg
Author-email: damien.goldenberg@tinyclues.com
License: UNKNOWN
Keywords: quay,client
Platform: UNKNOWN
Classifier: Development Status :: 2 - Pre-Alpha
Classifier: Natural Language :: English
Classifier: Programming Language :: Python :: 2.7
Requires-Dist: request-factory (==2)
